01.pre-study/07.Digital Logic Circuit experiments/03_alu/verilator/complement.v
module complement(
  input  wire [3:0] b,
  input  wire [2:0] option,
  output reg  [3:0] B
);
    //b的补码
    reg [3:0] temp = ~b + 4'h1;

    always @(*) begin
        case (option)
            3'b000: B = b;      //加法
            3'b001: B = temp;   //减法
            3'b010: B = b;      //取反
            3'b011: B = b;      //与
            3'b100: B = b;      //或
            3'b101: B = b;      //异或
            3'b110: B = temp;   //比较大小
            3'b111: B = temp;   //判断相等
            default: ;
        endcase
    end
endmodule

01.pre-study/07.Digital Logic Circuit experiments/03_alu/verilator/top.v
module top(
  input  wire [3:0] A,
  input  wire [3:0] b,
  input  wire [2:0] option,
  output reg        carry,
  output reg        overflow,
  output reg        zero,
  output reg  [3:0] result
);

  wire [3:0] a_s;
  wire       a_cin;
  reg  [3:0] B;
  //补码模块
  complement  complement_inst(
    .b      (b),
    .option (option),
    .B      (B));


  assign {a_cin, a_s} = A + B;

  //carry
  always @(*) begin
    case (option)
      3'b000: carry = a_cin;  //加法
      3'b001: carry = a_cin;  //减法
      3'b010: carry = 1'b0;   //取反
      3'b011: carry = 1'b0;   //与
      3'b100: carry = 1'b0;   //或
      3'b101: carry = 1'b0;   //异或
      3'b110: carry = a_cin;  //比较大小
      3'b111: carry = a_cin;  //判断相等
      default: ;
    endcase    
  end

  //overflow
  reg overflow_temp;
  assign overflow_temp = (A[3]==B[3]) && (A[3]!=a_s[3]);
  always @(*) begin
    case (option)
      3'b000: overflow = overflow_temp;  //带符号加法
      3'b001: overflow = overflow_temp;  //带符号减法
      3'b010: overflow = 1'b0;           //取反
      3'b011: overflow = 1'b0;           //与
      3'b100: overflow = 1'b0;           //或
      3'b101: overflow = 1'b0;           //异或
      3'b110: overflow = overflow_temp;  //带符号比较大小
      3'b111: overflow = overflow_temp;  //判断相等
      default: ;
    endcase    
  end

  assign zero = ~(|a_s);

  //result
  always @(*) begin
    case (option)
      3'b000: result = a_s;                              //加法
      3'b001: result = a_s;                              //减法
      3'b010: result = A ^ 4'hf;                         //取反
      3'b011: result = A & B;                            //与
      3'b100: result = A | B;                            //或
      3'b101: result = A ^ B;                            //异或
      3'b110: result = {3'd0, a_s[3] ^ overflow_temp};   //比较大小
      3'b111: result = {3'd0, {zero}};                   //判断相等
      default: ;
    endcase    
  end
endmodule

01.pre-study/07.Digital Logic Circuit experiments/03_alu/verilator/waveform.vcd
$version Generated by VerilatedVcd $end
$date Tue Feb  6 12:43:49 2024 $end
$timescale 1ps $end

 $scope module TOP $end
  $var wire  4 ' A [3:0] $end
  $var wire  4 ( b [3:0] $end
  $var wire  1 * carry $end
  $var wire  3 ) option [2:0] $end
  $var wire  1 + overflow $end
  $var wire  4 - result [3:0] $end
  $var wire  1 , zero $end
  $scope module top $end
   $var wire  4 ' A [3:0] $end
   $var wire  4 % B [3:0] $end
   $var wire  1 $ a_cin $end
   $var wire  4 # a_s [3:0] $end
   $var wire  4 ( b [3:0] $end
   $var wire  1 * carry $end
   $var wire  3 ) option [2:0] $end
   $var wire  1 + overflow $end
   $var wire  1 & overflow_temp $end
   $var wire  4 - result [3:0] $end
   $var wire  1 , zero $end
   $scope module complement_inst $end
    $var wire  4 % B [3:0] $end
    $var wire  4 ( b [3:0] $end
    $var wire  3 ) option [2:0] $end
    $var wire  4 . temp [3:0] $end
   $upscope $end
  $upscope $end
 $upscope $end
$enddefinitions $end


#1
b0000 #
0$
b0000 %
0&
b0000 '
b0000 (
b000 )
0*
0+
1,
b0000 -
b0000 .
#2
b1111 #
b1100 %
b0011 '
b1100 (
b010 )
0,
b1100 -
b0100 .
#3
b011 )
b0000 -
#4
b100 )
b1111 -
#5
b101 )
#6
b0111 #
b0100 %
b110 )
b0000 -
#7
b1001 #
1$
b1101 %
b1100 '
b0011 (
1*
b0001 -
b1101 .
#8
b0000 #
b0100 %
b1100 (
1,
b0000 -
b0100 .
#9
b111 )
b0001 -
#10
b1001 #
b1101 %
b0011 (
0,
b0000 -
b1101 .
#11
b0111 #
0$
b0100 %
b0011 '
b1100 (
0*
b0100 .
